{"DocumentConnection":{"type":"DocumentConnection","resolveType":"multiCollectionDocumentList","collections":["page","websiteDetails"]},"Node":{"type":"Node","resolveType":"nodeDocument"},"DocumentNode":{"type":"DocumentNode","resolveType":"multiCollectionDocument","createDocument":"create","updateDocument":"update"},"Post":{"type":"Post","resolveType":"collectionDocument","collection":"post","createPost":"create","updatePost":"update"},"PostConnection":{"type":"PostConnection","resolveType":"collectionDocumentList","collection":"post"},"WebLinks":{"type":"WebLinks","resolveType":"collectionDocument","collection":"webLinks","createWebLinks":"create","updateWebLinks":"update"},"WebLinksConnection":{"type":"WebLinksConnection","resolveType":"collectionDocumentList","collection":"webLinks"},"WebLink":{"type":"WebLink","resolveType":"collectionDocument","collection":"webLink","createWebLink":"create","updateWebLink":"update"},"WebLinkConnection":{"type":"WebLinkConnection","resolveType":"collectionDocumentList","collection":"webLink"},"About":{"type":"About","resolveType":"collectionDocument","collection":"about","createAbout":"create","updateAbout":"update"},"AboutConnection":{"type":"AboutConnection","resolveType":"collectionDocumentList","collection":"about"},"Intro":{"type":"Intro","resolveType":"collectionDocument","collection":"intro","createIntro":"create","updateIntro":"update"},"IntroConnection":{"type":"IntroConnection","resolveType":"collectionDocumentList","collection":"intro"},"TeamMembers":{"type":"TeamMembers","resolveType":"collectionDocument","collection":"teamMembers","createTeamMembers":"create","updateTeamMembers":"update"},"TeamMembersConnection":{"type":"TeamMembersConnection","resolveType":"collectionDocumentList","collection":"teamMembers"},"Page":{"type":"Page","resolveType":"unionData","collection":"page","typeMap":{"about":"PageAbout","partners":"PagePartners","impact":"PageImpact","contact":"PageContact","raceInfo":"PageRaceInfo"}},"PageConnection":{"type":"PageConnection","resolveType":"collectionDocumentList","collection":"page"},"WebsiteDetails":{"type":"WebsiteDetails","resolveType":"unionData","collection":"websiteDetails","typeMap":{"webLinks":"WebsiteDetailsWebLinks","faq":"WebsiteDetailsFaq","navLinks":"WebsiteDetailsNavLinks","cta":"WebsiteDetailsCta","customBackground":"WebsiteDetailsCustomBackground"}},"WebsiteDetailsConnection":{"type":"WebsiteDetailsConnection","resolveType":"collectionDocumentList","collection":"websiteDetails"}}