{"version":{"fullVersion":"1.3.5","major":"1","minor":"3","patch":"5"},"meta":{"flags":["experimentalData","isomorphicGitBridge"]},"collections":[{"name":"page","label":"Website Pages","path":"content/pages","format":"md","ui":{},"templates":[{"name":"about","label":"About","fields":[{"type":"image","name":"picture","label":"Picture","namespace":["page","about","picture"]},{"type":"string","name":"alt","label":"Picture Description (accessibility)","namespace":["page","about","alt"]},{"type":"rich-text","name":"intro","label":"Intro","namespace":["page","about","intro"]},{"type":"string","name":"cta","label":"CTA","namespace":["page","about","cta"]},{"label":"Team Members","name":"teamMembers","type":"object","list":true,"ui":{},"fields":[{"type":"image","label":"Headshot","name":"headshot","namespace":["page","about","teamMembers","headshot"]},{"label":"First Name","name":"firstName","type":"string","namespace":["page","about","teamMembers","firstName"]},{"label":"Last Name","name":"lastName","type":"string","namespace":["page","about","teamMembers","lastName"]},{"label":"Role","name":"role","type":"string","namespace":["page","about","teamMembers","role"]},{"label":"Bio","name":"bio","type":"string","ui":{"component":"textarea"},"namespace":["page","about","teamMembers","bio"]}],"namespace":["page","about","teamMembers"]}],"namespace":["page","about"]},{"name":"partners","label":"Partners","fields":[{"type":"image","name":"picture","label":"Picture","namespace":["page","partners","picture"]},{"type":"string","name":"alt","label":"Picture Description (accessibility)","namespace":["page","partners","alt"]},{"type":"rich-text","name":"intro","label":"Intro","namespace":["page","partners","intro"]},{"label":"Partners Data","name":"partnersData","type":"object","list":true,"ui":{"max":2},"fields":[{"label":"Tab Title","name":"tabTitle","type":"string","namespace":["page","partners","partnersData","tabTitle"]},{"label":"Intro","name":"intro","type":"string","ui":{"component":"textarea"},"namespace":["page","partners","partnersData","intro"]},{"label":"Call To Action","name":"callToAction","type":"string","namespace":["page","partners","partnersData","callToAction"]},{"label":"Partner Sign-Up Form","name":"form","type":"object","fields":[{"label":"Placeholder Logo","name":"logo","type":"image","namespace":["page","partners","partnersData","form","logo"]},{"label":"Email Form to:","name":"email","type":"string","required":true,"namespace":["page","partners","partnersData","form","email"]},{"label":"Call To Action","name":"callToAction","type":"string","namespace":["page","partners","partnersData","form","callToAction"]},{"label":"Form Title","name":"title","type":"string","namespace":["page","partners","partnersData","form","title"]},{"label":"Details and Benefits","name":"details","type":"rich-text","namespace":["page","partners","partnersData","form","details"]},{"label":"Form Fields","name":"fields","type":"object","list":true,"ui":{},"fields":[{"label":"Field Name","name":"fieldName","type":"string","required":true,"namespace":["page","partners","partnersData","form","fields","fieldName"]},{"label":"Type","name":"type","type":"string","required":true,"options":[{"value":"Short answer text","label":"Short Answer"},{"value":"Paragraph","label":"Paragraph"},{"value":"Email","label":"Email"},{"value":"Checkbox","label":"Checkbox"},{"value":"Disclaimer","label":"Disclaimer"}],"namespace":["page","partners","partnersData","form","fields","type"]},{"label":"Placeholder","name":"placeholder","type":"string","required":true,"ui":{"component":"textarea"},"namespace":["page","partners","partnersData","form","fields","placeholder"]},{"label":"Required","name":"required","type":"boolean","required":true,"namespace":["page","partners","partnersData","form","fields","required"]},{"label":"Options","name":"options","type":"string","list":true,"namespace":["page","partners","partnersData","form","fields","options"]}],"namespace":["page","partners","partnersData","form","fields"]}],"namespace":["page","partners","partnersData","form"]},{"label":"Companies or Schools","name":"companies","type":"object","list":true,"ui":{},"fields":[{"label":"Logo","name":"logo","type":"image","required":true,"namespace":["page","partners","partnersData","companies","logo"]},{"label":"Name","name":"name","type":"string","required":true,"namespace":["page","partners","partnersData","companies","name"]},{"label":"Description","name":"description","type":"string","ui":{"component":"textarea"},"namespace":["page","partners","partnersData","companies","description"]},{"label":"Website","name":"website","type":"string","required":true,"namespace":["page","partners","partnersData","companies","website"]},{"label":"Displayed on HomePage","name":"homepage","type":"boolean","namespace":["page","partners","partnersData","companies","homepage"]}],"namespace":["page","partners","partnersData","companies"]}],"namespace":["page","partners","partnersData"]}],"namespace":["page","partners"]},{"name":"impact","label":"Impact","fields":[{"name":"milestones","label":"Impact Milestones","type":"object","list":true,"ui":{},"fields":[{"name":"title","label":"Title","type":"string","required":true,"namespace":["page","impact","milestones","title"]},{"name":"description","label":"Description","type":"string","required":true,"ui":{"component":"textarea"},"namespace":["page","impact","milestones","description"]}],"namespace":["page","impact","milestones"]},{"name":"communityTitle","label":"Community Title","type":"string","namespace":["page","impact","communityTitle"]},{"name":"smallIntro","label":"Community Intro Text","type":"string","ui":{"component":"textarea"},"namespace":["page","impact","smallIntro"]},{"name":"communityMembers","label":"Community Members","type":"object","list":true,"ui":{"max":2},"fields":[{"name":"tabTitle","label":"Tab Title","type":"string","namespace":["page","impact","communityMembers","tabTitle"]},{"name":"tabIntro","label":"Tab Intro","type":"string","ui":{"component":"textarea"},"namespace":["page","impact","communityMembers","tabIntro"]},{"name":"profiles","label":"Member Profiles","type":"object","list":true,"ui":{},"fields":[{"name":"picture","label":"Picture","type":"image","namespace":["page","impact","communityMembers","profiles","picture"]},{"name":"firstName","label":"First Name","type":"string","namespace":["page","impact","communityMembers","profiles","firstName"]},{"name":"lastName","label":"Last Name","type":"string","namespace":["page","impact","communityMembers","profiles","lastName"]},{"name":"schoolOrEvent","label":"School/Event","type":"string","namespace":["page","impact","communityMembers","profiles","schoolOrEvent"]},{"name":"year","label":"Year","type":"number","namespace":["page","impact","communityMembers","profiles","year"]},{"name":"bio","label":"Bio/Testimonial","type":"string","ui":{"component":"textarea"},"namespace":["page","impact","communityMembers","profiles","bio"]}],"namespace":["page","impact","communityMembers","profiles"]}],"namespace":["page","impact","communityMembers"]}],"namespace":["page","impact"]},{"name":"contact","label":"Contact","fields":[{"name":"formTitle","label":"Form Title","type":"string","namespace":["page","contact","formTitle"]},{"name":"formSubmit","label":"Form Submit Text","type":"string","namespace":["page","contact","formSubmit"]},{"label":"Email Form to:","name":"email","type":"string","required":true,"namespace":["page","contact","email"]},{"name":"formFields","label":"Contact Form Fields","type":"object","list":true,"ui":{},"fields":[{"label":"Field Name","name":"fieldName","type":"string","required":true,"namespace":["page","contact","formFields","fieldName"]},{"label":"Type","name":"type","type":"string","required":true,"options":[{"value":"Short answer text","label":"Short Answer"},{"value":"Paragraph","label":"Paragraph"},{"value":"Email","label":"Email"},{"value":"Checkbox","label":"Checkbox"},{"value":"Disclaimer","label":"Disclaimer"}],"namespace":["page","contact","formFields","type"]},{"label":"Placeholder","name":"placeholder","type":"string","required":true,"ui":{"component":"textarea"},"namespace":["page","contact","formFields","placeholder"]},{"label":"Required","name":"required","type":"boolean","required":true,"namespace":["page","contact","formFields","required"]},{"label":"Options","name":"options","type":"string","list":true,"namespace":["page","contact","formFields","options"]}],"namespace":["page","contact","formFields"]},{"name":"socialTitle","label":"Title for Social Media Links","type":"string","namespace":["page","contact","socialTitle"]},{"name":"links","label":"Social Media Links","type":"object","list":true,"ui":{},"fields":[{"name":"type","label":"Link Type","type":"string","options":["Email","Instagram","Facebook","YouTube","TikTok","LinkedIn"],"namespace":["page","contact","links","type"]},{"name":"text","label":"Link Text","type":"string","namespace":["page","contact","links","text"]}],"namespace":["page","contact","links"]}],"namespace":["page","contact"]},{"name":"raceInfo","label":"Registration Page","fields":[{"name":"raceDay","label":"Race Day (Start Date)","type":"object","fields":[{"name":"year","label":"Year","type":"number","namespace":["page","raceInfo","raceDay","year"]},{"name":"month","label":"Month","type":"number","ui":{},"namespace":["page","raceInfo","raceDay","month"]},{"name":"day","label":"Day","type":"number","ui":{},"namespace":["page","raceInfo","raceDay","day"]}],"namespace":["page","raceInfo","raceDay"]},{"name":"raceInfoIntro","label":"Intro Text","type":"rich-text","namespace":["page","raceInfo","raceInfoIntro"]},{"name":"cta","label":"Call To Action","type":"string","namespace":["page","raceInfo","cta"]},{"name":"benefits","label":"Race Benefits","type":"object","list":true,"ui":{},"fields":[{"name":"title","label":"Benefit Title","type":"string","namespace":["page","raceInfo","benefits","title"]},{"name":"imageIcon","label":"Benefit Picture","type":"image","namespace":["page","raceInfo","benefits","imageIcon"]}],"namespace":["page","raceInfo","benefits"]},{"name":"tickets","label":"Tickets","type":"object","list":true,"ui":{},"fields":[{"name":"title","label":"Ticket Title","type":"string","namespace":["page","raceInfo","tickets","title"]},{"name":"description","label":"Description","type":"string","namespace":["page","raceInfo","tickets","description"]},{"name":"price","label":"Price","type":"string","namespace":["page","raceInfo","tickets","price"]},{"name":"fee","label":"Run Sign-Up Fee","type":"string","namespace":["page","raceInfo","tickets","fee"]},{"name":"mostPopular","label":"Most Popular Option","type":"boolean","namespace":["page","raceInfo","tickets","mostPopular"]},{"name":"inPerson","label":"In-Person Event","type":"boolean","namespace":["page","raceInfo","tickets","inPerson"]},{"name":"link","label":"Registration Link","type":"string","namespace":["page","raceInfo","tickets","link"]},{"name":"features","label":"Features","type":"string","list":true,"namespace":["page","raceInfo","tickets","features"]}],"namespace":["page","raceInfo","tickets"]},{"name":"otherOptions","label":"Other Participation Options","type":"string","ui":{"component":"textarea"},"namespace":["page","raceInfo","otherOptions"]},{"name":"donateCTA","label":"Donation CTA","type":"string","namespace":["page","raceInfo","donateCTA"]},{"name":"donate","label":"Donation Link","type":"string","namespace":["page","raceInfo","donate"]},{"name":"sponsorStudentCTA","label":"Student Runner CTA","type":"string","namespace":["page","raceInfo","sponsorStudentCTA"]},{"name":"sponsorStudent","label":"Student Runner Link","type":"string","namespace":["page","raceInfo","sponsorStudent"]},{"name":"pastEvents","label":"Past Events","type":"object","list":true,"ui":{},"fields":[{"name":"type","label":"Event Type","type":"string","options":[{"value":"recap","label":"Annual Recap"},{"value":"event","label":"Individual Event"}],"namespace":["page","raceInfo","pastEvents","type"]},{"name":"date","label":"Date","type":"string","namespace":["page","raceInfo","pastEvents","date"]},{"name":"title","label":"Event Name","type":"string","namespace":["page","raceInfo","pastEvents","title"]},{"name":"highlights","label":"Event Highlights","type":"string","list":true,"namespace":["page","raceInfo","pastEvents","highlights"]},{"name":"pictures","label":"Pictures","type":"object","list":true,"ui":{},"fields":[{"name":"picture","label":"Picture","type":"image","namespace":["page","raceInfo","pastEvents","pictures","picture"]},{"name":"alt","label":"Image Description (accessibility)","type":"string","namespace":["page","raceInfo","pastEvents","pictures","alt"]}],"namespace":["page","raceInfo","pastEvents","pictures"]},{"name":"video","label":"Recap Video","type":"image","namespace":["page","raceInfo","pastEvents","video"]}],"namespace":["page","raceInfo","pastEvents"]}],"namespace":["page","raceInfo"]},{"name":"homepage","label":"Homepage","fields":[{"name":"heroSection","label":"Hero Banner","type":"object","fields":[{"name":"heroVideo","label":"Welcome Video","type":"image","namespace":["page","homepage","heroSection","heroVideo"]},{"name":"heroVideoThumbnail","label":"Welcome Video Thumbnail","type":"image","namespace":["page","homepage","heroSection","heroVideoThumbnail"]},{"name":"slogan","label":"Slogan","type":"string","namespace":["page","homepage","heroSection","slogan"]},{"name":"button","label":"Button","type":"string","namespace":["page","homepage","heroSection","button"]}],"namespace":["page","homepage","heroSection"]},{"name":"mainCTA","label":"Call To Action Section","type":"object","list":true,"ui":{"max":3},"fields":[{"name":"name","label":"CTA Main","type":"string","namespace":["page","homepage","mainCTA","name"]},{"name":"description","label":"CTA Description","type":"string","namespace":["page","homepage","mainCTA","description"]},{"name":"image","label":"CTA Image","type":"image","namespace":["page","homepage","mainCTA","image"]},{"type":"string","name":"alt","label":"CTA Image Description (accessibility)","namespace":["page","homepage","mainCTA","alt"]}],"namespace":["page","homepage","mainCTA"]},{"name":"stats","label":"Homepage Statistics","type":"object","fields":[{"name":"stat1","label":"Statistic #1","type":"string","namespace":["page","homepage","stats","stat1"]},{"name":"stat1Description","label":"Statistic #1 Description","type":"string","namespace":["page","homepage","stats","stat1Description"]},{"name":"stat2","label":"Statistic #2","type":"string","namespace":["page","homepage","stats","stat2"]},{"name":"stat2Description","label":"Statistic #2 Description","type":"string","namespace":["page","homepage","stats","stat2Description"]},{"name":"cta","label":"Call To Action","type":"string","namespace":["page","homepage","stats","cta"]}],"namespace":["page","homepage","stats"]},{"name":"pastEvents","label":"Homepage Past Events","type":"object","list":true,"ui":{"max":4},"fields":[{"name":"title","label":"Title","type":"string","namespace":["page","homepage","pastEvents","title"]},{"name":"picture","label":"Picture","type":"image","namespace":["page","homepage","pastEvents","picture"]},{"type":"string","name":"alt","label":"Picture Description (accessibility)","namespace":["page","homepage","pastEvents","alt"]}],"namespace":["page","homepage","pastEvents"]},{"name":"mission","label":"Mission","type":"object","fields":[{"name":"image","label":"Picture","type":"image","namespace":["page","homepage","mission","image"]},{"type":"string","name":"alt","label":"Picture Description (accessibility)","namespace":["page","homepage","mission","alt"]},{"name":"title","label":"Title","type":"string","namespace":["page","homepage","mission","title"]},{"name":"mission","label":"Mission","type":"string","ui":{"component":"textarea"},"namespace":["page","homepage","mission","mission"]},{"name":"button","label":"Button","type":"string","namespace":["page","homepage","mission","button"]}],"namespace":["page","homepage","mission"]},{"name":"newsletterSignUp","label":"Newsletter Sign-Up Form","type":"object","fields":[{"name":"title","label":"Title","type":"string","namespace":["page","homepage","newsletterSignUp","title"]},{"name":"description","label":"Description","type":"string","ui":{"component":"textarea"},"namespace":["page","homepage","newsletterSignUp","description"]},{"name":"button","label":"Button","type":"string","namespace":["page","homepage","newsletterSignUp","button"]},{"label":"Email Form to:","name":"email","type":"string","required":true,"namespace":["page","homepage","newsletterSignUp","email"]},{"name":"formFields","label":"Form Fields","type":"object","list":true,"ui":{},"fields":[{"label":"Field Name","name":"fieldName","type":"string","required":true,"namespace":["page","homepage","newsletterSignUp","formFields","fieldName"]},{"label":"Type","name":"type","type":"string","required":true,"options":[{"value":"Short answer text","label":"Short Answer"},{"value":"Paragraph","label":"Paragraph"},{"value":"Email","label":"Email"},{"value":"Checkbox","label":"Checkbox"},{"value":"Disclaimer","label":"Disclaimer"}],"namespace":["page","homepage","newsletterSignUp","formFields","type"]},{"label":"Placeholder","name":"placeholder","type":"string","required":true,"ui":{"component":"textarea"},"namespace":["page","homepage","newsletterSignUp","formFields","placeholder"]},{"label":"Required","name":"required","type":"boolean","required":true,"namespace":["page","homepage","newsletterSignUp","formFields","required"]},{"label":"Options","name":"options","type":"string","list":true,"namespace":["page","homepage","newsletterSignUp","formFields","options"]}],"namespace":["page","homepage","newsletterSignUp","formFields"]}],"namespace":["page","homepage","newsletterSignUp"]}],"namespace":["page","homepage"]}],"namespace":["page"]},{"name":"websiteDetails","label":"Site Details","path":"content/siteDetails","format":"md","templates":[{"name":"webLinks","label":"Links","fields":[{"type":"string","name":"quote","label":"Quote","namespace":["websiteDetails","webLinks","quote"]},{"name":"socialLinks","label":"Social Media Links","type":"object","list":true,"ui":{},"fields":[{"name":"platform","label":"Platform","type":"string","options":["Email","Instagram","Facebook","YouTube","TikTok","LinkedIn"],"namespace":["websiteDetails","webLinks","socialLinks","platform"]},{"name":"link","label":"Link","type":"string","namespace":["websiteDetails","webLinks","socialLinks","link"]},{"name":"showIcon","label":"Show Icon","type":"boolean","namespace":["websiteDetails","webLinks","socialLinks","showIcon"]}],"namespace":["websiteDetails","webLinks","socialLinks"]}],"namespace":["websiteDetails","webLinks"]},{"name":"faq","label":"FAQ","fields":[{"name":"faq","label":"Frequently Asked Questions","type":"object","list":true,"ui":{},"fields":[{"name":"question","label":"Question","type":"string","ui":{"component":"textarea"},"namespace":["websiteDetails","faq","faq","question"]},{"name":"answer","label":"Answer","type":"rich-text","namespace":["websiteDetails","faq","faq","answer"]}],"namespace":["websiteDetails","faq","faq"]}],"namespace":["websiteDetails","faq"]},{"name":"navLinks","label":"Navigation Links","fields":[{"name":"navLinks","label":"Navigation Links and Banner Images","type":"object","list":true,"ui":{},"fields":[{"name":"bannerImage","label":"Banner Image","type":"image","namespace":["websiteDetails","navLinks","navLinks","bannerImage"]},{"type":"string","name":"bannerImageAlt","label":"Banner Image Description (accessibility)","namespace":["websiteDetails","navLinks","navLinks","bannerImageAlt"]},{"name":"pageTitle","label":"Page Title","type":"string","namespace":["websiteDetails","navLinks","navLinks","pageTitle"]},{"name":"path","label":"Path (DO NOT EDIT)","type":"string","namespace":["websiteDetails","navLinks","navLinks","path"]},{"name":"pageDescription","label":"Page Description (SEO)","type":"string","ui":{"component":"textarea"},"namespace":["websiteDetails","navLinks","navLinks","pageDescription"]},{"name":"pageImage","label":"Page Image (SEO)","type":"image","namespace":["websiteDetails","navLinks","navLinks","pageImage"]},{"name":"highlight","label":"Highlight Link","type":"boolean","namespace":["websiteDetails","navLinks","navLinks","highlight"]},{"name":"bannerImageLarge","label":"Banner Image (Large)","type":"image","namespace":["websiteDetails","navLinks","navLinks","bannerImageLarge"]}],"namespace":["websiteDetails","navLinks","navLinks"]}],"namespace":["websiteDetails","navLinks"]},{"name":"cta","label":"CTA","fields":[{"name":"image","label":"Picture","type":"image","namespace":["websiteDetails","cta","image"]},{"type":"string","name":"alt","label":"Picture Description (accessibility)","namespace":["websiteDetails","cta","alt"]},{"name":"title","label":"CTA Title","type":"string","namespace":["websiteDetails","cta","title"]},{"name":"text","label":"CTA Text","type":"string","ui":{"component":"textarea"},"namespace":["websiteDetails","cta","text"]},{"name":"button","label":"CTA Button","type":"string","namespace":["websiteDetails","cta","button"]}],"namespace":["websiteDetails","cta"]},{"name":"customBackground","label":"Custom Background","fields":[{"name":"customBackground","label":"Custom Background","type":"image","namespace":["websiteDetails","customBackground","customBackground"]}],"namespace":["websiteDetails","customBackground"]}],"namespace":["websiteDetails"]}],"config":{"media":{"tina":{"publicFolder":"public","mediaRoot":"images"}}}}